PCLTheme/__init__.py
PCLTheme/build.py
PCLTheme/global_var.py
PCLTheme/Controls/__init__.py
PCLTheme/Controls/gird.py
PCLTheme/Controls/my_button.py
PCLTheme/Controls/my_card.py
PCLTheme/Controls/my_hint.py
PCLTheme/Controls/my_icon_button.py
PCLTheme/Controls/my_icon_text_button.py
PCLTheme/Controls/my_image.py
PCLTheme/Controls/my_list_item.py
PCLTheme/Controls/my_text_button.py
PCLTheme/Controls/stack_panel.py
PCLTheme/Controls/text_block.py
PCLTheme/Controls/warp_panel.py
pcltheme-0.2.3.dist-info/licenses/LICENSE
pcltheme-0.2.3.dist-info/METADATA
pcltheme-0.2.3.dist-info/WHEEL
pcltheme-0.2.3.dist-info/top_level.txt
pcltheme-0.2.3.dist-info/RECORD
