Metadata-Version: 2.4
Name: PCLTheme
Version: 0.2.3
Summary: 用 Python 构建 PCL XAML 模板的轻量库
Author-email: just-ugly <just_ugly@163.com>
License: MIT
Keywords: pcl,xaml,theme
Classifier: Programming Language :: Python :: 3
Classifier: Programming Language :: Python :: 3.8
Classifier: Programming Language :: Python :: 3.9
Classifier: Programming Language :: Python :: 3.10
Classifier: Programming Language :: Python :: 3.11
Classifier: Programming Language :: Python :: 3.12
Classifier: License :: OSI Approved :: MIT License
Classifier: Operating System :: OS Independent
Requires-Python: >=3.6
License-File: LICENSE
Requires-Dist: chameleon
Requires-Dist: pydantic
Dynamic: license-file
